avnum/__init__.py
avnum/avnum.py
avnum-1.1.dist-info/METADATA
avnum-1.1.dist-info/WHEEL
avnum-1.1.dist-info/top_level.txt
avnum-1.1.dist-info/RECORD
