Metadata-Version: 2.1
Name: avnum
Version: 1.1
Summary: A simple module to calculate the average of numbers
Home-page: https://github.com/andreimotin/avnum
Author: Andrei Motin
Author-email: motinandrei@icloud.com
Classifier: Programming Language :: Python :: 3
Classifier: License :: OSI Approved :: MIT License
Classifier: Operating System :: OS Independent
Requires-Python: >=3.6
